{
  "name": "BackupResourceEncryptionConfig",
  "fields": [
    {
      "containsDiscriminatedTypeValue": false,
      "jsonName": "encryptionAtRestType",
      "name": "EncryptionAtRestType",
      "objectDefinition": {
        "type": "Reference",
        "referenceName": "EncryptionAtRestType"
      },
      "optional": true,
      "required": false,
      "description": ""
    },
    {
      "containsDiscriminatedTypeValue": false,
      "jsonName": "infrastructureEncryptionState",
      "name": "InfrastructureEncryptionState",
      "objectDefinition": {
        "type": "Reference",
        "referenceName": "InfrastructureEncryptionState"
      },
      "optional": true,
      "required": false,
      "description": ""
    },
    {
      "containsDiscriminatedTypeValue": false,
      "jsonName": "keyUri",
      "name": "KeyUri",
      "objectDefinition": {
        "type": "String",
        "referenceName": null
      },
      "optional": true,
      "required": false,
      "description": ""
    },
    {
      "containsDiscriminatedTypeValue": false,
      "jsonName": "lastUpdateStatus",
      "name": "LastUpdateStatus",
      "objectDefinition": {
        "type": "Reference",
        "referenceName": "LastUpdateStatus"
      },
      "optional": true,
      "required": false,
      "description": ""
    },
    {
      "containsDiscriminatedTypeValue": false,
      "jsonName": "subscriptionId",
      "name": "SubscriptionId",
      "objectDefinition": {
        "type": "String",
        "referenceName": null
      },
      "optional": true,
      "required": false,
      "description": ""
    }
  ]
}