{
  "name": "CorsPolicy",
  "fields": [
    {
      "containsDiscriminatedTypeValue": false,
      "description": "Specifies whether the resource allows credentials",
      "jsonName": "allowCredentials",
      "name": "AllowCredentials",
      "objectDefinition": {
        "type": "Boolean",
        "nullable": false,
        "referenceName": null,
        "referenceNameIsCommonType": null
      },
      "optional": true,
      "readOnly": false,
      "required": false,
      "sensitive": false
    },
    {
      "containsDiscriminatedTypeValue": false,
      "description": "Specifies the content for the access-control-allow-headers header",
      "jsonName": "allowedHeaders",
      "name": "AllowedHeaders",
      "objectDefinition": {
        "type": "List",
        "nullable": false,
        "referenceName": null,
        "referenceNameIsCommonType": null,
        "nestedItem": {
          "type": "String",
          "nullable": false,
          "referenceName": null,
          "referenceNameIsCommonType": null
        }
      },
      "optional": true,
      "readOnly": false,
      "required": false,
      "sensitive": false
    },
    {
      "containsDiscriminatedTypeValue": false,
      "description": "Specifies the content for the access-control-allow-methods header",
      "jsonName": "allowedMethods",
      "name": "AllowedMethods",
      "objectDefinition": {
        "type": "List",
        "nullable": false,
        "referenceName": null,
        "referenceNameIsCommonType": null,
        "nestedItem": {
          "type": "String",
          "nullable": false,
          "referenceName": null,
          "referenceNameIsCommonType": null
        }
      },
      "optional": true,
      "readOnly": false,
      "required": false,
      "sensitive": false
    },
    {
      "containsDiscriminatedTypeValue": false,
      "description": "Specifies the content for the access-control-allow-origins header",
      "jsonName": "allowedOrigins",
      "name": "AllowedOrigins",
      "objectDefinition": {
        "type": "List",
        "nullable": false,
        "referenceName": null,
        "referenceNameIsCommonType": null,
        "nestedItem": {
          "type": "String",
          "nullable": false,
          "referenceName": null,
          "referenceNameIsCommonType": null
        }
      },
      "optional": false,
      "readOnly": false,
      "required": true,
      "sensitive": false
    },
    {
      "containsDiscriminatedTypeValue": false,
      "description": "Specifies the content for the access-control-expose-headers header ",
      "jsonName": "exposeHeaders",
      "name": "ExposeHeaders",
      "objectDefinition": {
        "type": "List",
        "nullable": false,
        "referenceName": null,
        "referenceNameIsCommonType": null,
        "nestedItem": {
          "type": "String",
          "nullable": false,
          "referenceName": null,
          "referenceNameIsCommonType": null
        }
      },
      "optional": true,
      "readOnly": false,
      "required": false,
      "sensitive": false
    },
    {
      "containsDiscriminatedTypeValue": false,
      "description": "Specifies the content for the access-control-max-age header",
      "jsonName": "maxAge",
      "name": "MaxAge",
      "objectDefinition": {
        "type": "Integer",
        "nullable": false,
        "referenceName": null,
        "referenceNameIsCommonType": null
      },
      "optional": true,
      "readOnly": false,
      "required": false,
      "sensitive": false
    }
  ],
  "IsParent": false
}