{
  "name": "DscCompilationJobProperties",
  "fields": [
    {
      "containsDiscriminatedTypeValue": false,
      "description": "Gets or sets the configuration.",
      "jsonName": "configuration",
      "name": "Configuration",
      "objectDefinition": {
        "type": "Reference",
        "nullable": false,
        "referenceName": "DscConfigurationAssociationProperty",
        "referenceNameIsCommonType": null
      },
      "optional": true,
      "readOnly": false,
      "required": false,
      "sensitive": false
    },
    {
      "containsDiscriminatedTypeValue": false,
      "dateFormat": "RFC3339",
      "description": "Gets the creation time of the job.",
      "jsonName": "creationTime",
      "name": "CreationTime",
      "objectDefinition": {
        "type": "DateTime",
        "nullable": false,
        "referenceName": null,
        "referenceNameIsCommonType": null
      },
      "optional": true,
      "readOnly": false,
      "required": false,
      "sensitive": false
    },
    {
      "containsDiscriminatedTypeValue": false,
      "dateFormat": "RFC3339",
      "description": "Gets the end time of the job.",
      "jsonName": "endTime",
      "name": "EndTime",
      "objectDefinition": {
        "type": "DateTime",
        "nullable": false,
        "referenceName": null,
        "referenceNameIsCommonType": null
      },
      "optional": true,
      "readOnly": false,
      "required": false,
      "sensitive": false
    },
    {
      "containsDiscriminatedTypeValue": false,
      "description": "Gets the exception of the job.",
      "jsonName": "exception",
      "name": "Exception",
      "objectDefinition": {
        "type": "String",
        "nullable": false,
        "referenceName": null,
        "referenceNameIsCommonType": null
      },
      "optional": true,
      "readOnly": false,
      "required": false,
      "sensitive": false
    },
    {
      "containsDiscriminatedTypeValue": false,
      "description": "Gets the id of the job.",
      "jsonName": "jobId",
      "name": "JobId",
      "objectDefinition": {
        "type": "String",
        "nullable": false,
        "referenceName": null,
        "referenceNameIsCommonType": null
      },
      "optional": true,
      "readOnly": false,
      "required": false,
      "sensitive": false
    },
    {
      "containsDiscriminatedTypeValue": false,
      "dateFormat": "RFC3339",
      "description": "Gets the last modified time of the job.",
      "jsonName": "lastModifiedTime",
      "name": "LastModifiedTime",
      "objectDefinition": {
        "type": "DateTime",
        "nullable": false,
        "referenceName": null,
        "referenceNameIsCommonType": null
      },
      "optional": true,
      "readOnly": false,
      "required": false,
      "sensitive": false
    },
    {
      "containsDiscriminatedTypeValue": false,
      "dateFormat": "RFC3339",
      "description": "Gets the last status modified time of the job.",
      "jsonName": "lastStatusModifiedTime",
      "name": "LastStatusModifiedTime",
      "objectDefinition": {
        "type": "DateTime",
        "nullable": false,
        "referenceName": null,
        "referenceNameIsCommonType": null
      },
      "optional": true,
      "readOnly": false,
      "required": false,
      "sensitive": false
    },
    {
      "containsDiscriminatedTypeValue": false,
      "description": "Gets or sets the parameters of the job.",
      "jsonName": "parameters",
      "name": "Parameters",
      "objectDefinition": {
        "type": "Dictionary",
        "nullable": false,
        "referenceName": null,
        "referenceNameIsCommonType": null,
        "nestedItem": {
          "type": "String",
          "nullable": false,
          "referenceName": null,
          "referenceNameIsCommonType": null
        }
      },
      "optional": true,
      "readOnly": false,
      "required": false,
      "sensitive": false
    },
    {
      "containsDiscriminatedTypeValue": false,
      "description": "The current provisioning state of the job.",
      "jsonName": "provisioningState",
      "name": "ProvisioningState",
      "objectDefinition": {
        "type": "Reference",
        "nullable": false,
        "referenceName": "JobProvisioningState",
        "referenceNameIsCommonType": null
      },
      "optional": true,
      "readOnly": false,
      "required": false,
      "sensitive": false
    },
    {
      "containsDiscriminatedTypeValue": false,
      "description": "Gets or sets the runOn which specifies the group name where the job is to be executed.",
      "jsonName": "runOn",
      "name": "RunOn",
      "objectDefinition": {
        "type": "String",
        "nullable": false,
        "referenceName": null,
        "referenceNameIsCommonType": null
      },
      "optional": true,
      "readOnly": false,
      "required": false,
      "sensitive": false
    },
    {
      "containsDiscriminatedTypeValue": false,
      "dateFormat": "RFC3339",
      "description": "Gets the start time of the job.",
      "jsonName": "startTime",
      "name": "StartTime",
      "objectDefinition": {
        "type": "DateTime",
        "nullable": false,
        "referenceName": null,
        "referenceNameIsCommonType": null
      },
      "optional": true,
      "readOnly": false,
      "required": false,
      "sensitive": false
    },
    {
      "containsDiscriminatedTypeValue": false,
      "description": "Gets the compilation job started by.",
      "jsonName": "startedBy",
      "name": "StartedBy",
      "objectDefinition": {
        "type": "String",
        "nullable": false,
        "referenceName": null,
        "referenceNameIsCommonType": null
      },
      "optional": true,
      "readOnly": false,
      "required": false,
      "sensitive": false
    },
    {
      "containsDiscriminatedTypeValue": false,
      "description": "Gets or sets the status of the job.",
      "jsonName": "status",
      "name": "Status",
      "objectDefinition": {
        "type": "Reference",
        "nullable": false,
        "referenceName": "JobStatus",
        "referenceNameIsCommonType": null
      },
      "optional": true,
      "readOnly": false,
      "required": false,
      "sensitive": false
    },
    {
      "containsDiscriminatedTypeValue": false,
      "description": "Gets or sets the status details of the job.",
      "jsonName": "statusDetails",
      "name": "StatusDetails",
      "objectDefinition": {
        "type": "String",
        "nullable": false,
        "referenceName": null,
        "referenceNameIsCommonType": null
      },
      "optional": true,
      "readOnly": false,
      "required": false,
      "sensitive": false
    }
  ],
  "IsParent": false
}