{
  "name": "IdentityGovernanceEntitlementManagementAccessPackageCatalogIdAccessPackageResourceIdAccessPackageResourceScopeId",
  "id": "/identityGovernance/entitlementManagement/accessPackageCatalogs/{accessPackageCatalogId}/accessPackageResources/{accessPackageResourceId}/accessPackageResourceScopes/{accessPackageResourceScopeId}",
  "segments": [
    {
      "exampleValue": "",
      "name": "identityGovernance",
      "type": "Static",
      "value": "identityGovernance"
    },
    {
      "exampleValue": "",
      "name": "entitlementManagement",
      "type": "Static",
      "value": "entitlementManagement"
    },
    {
      "exampleValue": "",
      "name": "accessPackageCatalogs",
      "type": "Static",
      "value": "accessPackageCatalogs"
    },
    {
      "exampleValue": "accessPackageCatalogId",
      "name": "accessPackageCatalogId",
      "type": "UserSpecified"
    },
    {
      "exampleValue": "",
      "name": "accessPackageResources",
      "type": "Static",
      "value": "accessPackageResources"
    },
    {
      "exampleValue": "accessPackageResourceId",
      "name": "accessPackageResourceId",
      "type": "UserSpecified"
    },
    {
      "exampleValue": "",
      "name": "accessPackageResourceScopes",
      "type": "Static",
      "value": "accessPackageResourceScopes"
    },
    {
      "exampleValue": "accessPackageResourceScopeId",
      "name": "accessPackageResourceScopeId",
      "type": "UserSpecified"
    }
  ]
}