{
  "name": "PrivateLinkServiceConnectionState",
  "fields": [
    {
      "containsDiscriminatedTypeValue": false,
      "description": "Gets or sets actions required.",
      "jsonName": "actionsRequired",
      "name": "ActionsRequired",
      "objectDefinition": {
        "type": "String",
        "nullable": false,
        "referenceName": null,
        "referenceNameIsCommonType": null
      },
      "optional": true,
      "readOnly": false,
      "required": false,
      "sensitive": false
    },
    {
      "containsDiscriminatedTypeValue": false,
      "description": "Gets or sets description.",
      "jsonName": "description",
      "name": "Description",
      "objectDefinition": {
        "type": "String",
        "nullable": false,
        "referenceName": null,
        "referenceNameIsCommonType": null
      },
      "optional": true,
      "readOnly": false,
      "required": false,
      "sensitive": false
    },
    {
      "containsDiscriminatedTypeValue": false,
      "description": "Gets or sets the status.",
      "jsonName": "status",
      "name": "Status",
      "objectDefinition": {
        "type": "Reference",
        "nullable": false,
        "referenceName": "PrivateEndpointConnectionStatus",
        "referenceNameIsCommonType": null
      },
      "optional": true,
      "readOnly": false,
      "required": false,
      "sensitive": false
    }
  ],
  "IsParent": false
}