{
  "name": "ResourceAssociation",
  "fields": [
    {
      "containsDiscriminatedTypeValue": false,
      "description": "The access mode",
      "jsonName": "accessMode",
      "name": "AccessMode",
      "objectDefinition": {
        "type": "Reference",
        "nullable": false,
        "referenceName": "AccessMode",
        "referenceNameIsCommonType": null
      },
      "optional": true,
      "readOnly": false,
      "required": false,
      "sensitive": false
    },
    {
      "containsDiscriminatedTypeValue": false,
      "description": "Name of the Resource Association",
      "jsonName": "name",
      "name": "Name",
      "objectDefinition": {
        "type": "String",
        "nullable": false,
        "referenceName": null,
        "referenceNameIsCommonType": null
      },
      "optional": true,
      "readOnly": false,
      "required": false,
      "sensitive": false
    }
  ],
  "IsParent": false
}