{
  "name": "CertificateOrderStatus",
  "type": "String",
  "values": [
    {
      "key": "Canceled",
      "value": "Canceled"
    },
    {
      "key": "Denied",
      "value": "Denied"
    },
    {
      "key": "Expired",
      "value": "Expired"
    },
    {
      "key": "Issued",
      "value": "Issued"
    },
    {
      "key": "NotSubmitted",
      "value": "NotSubmitted"
    },
    {
      "key": "PendingRekey",
      "value": "PendingRekey"
    },
    {
      "key": "Pendingissuance",
      "value": "Pendingissuance"
    },
    {
      "key": "Pendingrevocation",
      "value": "Pendingrevocation"
    },
    {
      "key": "Revoked",
      "value": "Revoked"
    },
    {
      "key": "Unused",
      "value": "Unused"
    }
  ]
}