{
  "name": "NetworkInterfaceUpdate",
  "fields": [
    {
      "containsDiscriminatedTypeValue": false,
      "jsonName": "deviceKey",
      "name": "DeviceKey",
      "objectDefinition": {
        "type": "Integer",
        "nullable": false,
        "referenceName": null,
        "referenceNameIsCommonType": null
      },
      "optional": true,
      "readOnly": false,
      "required": false,
      "sensitive": false
    },
    {
      "containsDiscriminatedTypeValue": false,
      "jsonName": "name",
      "name": "Name",
      "objectDefinition": {
        "type": "String",
        "nullable": false,
        "referenceName": null,
        "referenceNameIsCommonType": null
      },
      "optional": true,
      "readOnly": false,
      "required": false,
      "sensitive": false
    },
    {
      "containsDiscriminatedTypeValue": false,
      "jsonName": "networkId",
      "name": "NetworkId",
      "objectDefinition": {
        "type": "String",
        "nullable": false,
        "referenceName": null,
        "referenceNameIsCommonType": null
      },
      "optional": true,
      "readOnly": false,
      "required": false,
      "sensitive": false
    },
    {
      "containsDiscriminatedTypeValue": false,
      "jsonName": "nicType",
      "name": "NicType",
      "objectDefinition": {
        "type": "Reference",
        "nullable": false,
        "referenceName": "NICType",
        "referenceNameIsCommonType": null
      },
      "optional": true,
      "readOnly": false,
      "required": false,
      "sensitive": false
    },
    {
      "containsDiscriminatedTypeValue": false,
      "jsonName": "powerOnBoot",
      "name": "PowerOnBoot",
      "objectDefinition": {
        "type": "Reference",
        "nullable": false,
        "referenceName": "PowerOnBootOption",
        "referenceNameIsCommonType": null
      },
      "optional": true,
      "readOnly": false,
      "required": false,
      "sensitive": false
    }
  ],
  "IsParent": false
}