{
 "name": "AutomationAccountProperties",
 "fields": [
  {
   "containsDiscriminatedTypeValue": false,
   "jsonName": "automationHybridServiceUrl",
   "name": "AutomationHybridServiceUrl",
   "objectDefinition": {
    "type": "String",
    "referenceName": null
   },
   "optional": true,
   "required": false,
   "description": "URL of automation hybrid service which is used for hybrid worker on-boarding."
  },
  {
   "containsDiscriminatedTypeValue": false,
   "jsonName": "creationTime",
   "name": "CreationTime",
   "objectDefinition": {
    "type": "DateTime",
    "referenceName": null,
    "dateFormat": "RFC3339"
   },
   "optional": true,
   "required": false,
   "description": "Gets the creation time."
  },
  {
   "containsDiscriminatedTypeValue": false,
   "jsonName": "description",
   "name": "Description",
   "objectDefinition": {
    "type": "String",
    "referenceName": null
   },
   "optional": true,
   "required": false,
   "description": "Gets or sets the description."
  },
  {
   "containsDiscriminatedTypeValue": false,
   "jsonName": "disableLocalAuth",
   "name": "DisableLocalAuth",
   "objectDefinition": {
    "type": "Boolean",
    "referenceName": null
   },
   "optional": true,
   "required": false,
   "description": "Indicates whether requests using non-AAD authentication are blocked"
  },
  {
   "containsDiscriminatedTypeValue": false,
   "jsonName": "encryption",
   "name": "Encryption",
   "objectDefinition": {
    "type": "Reference",
    "referenceName": "EncryptionProperties"
   },
   "optional": true,
   "required": false,
   "description": "Encryption properties for the automation account"
  },
  {
   "containsDiscriminatedTypeValue": false,
   "jsonName": "lastModifiedBy",
   "name": "LastModifiedBy",
   "objectDefinition": {
    "type": "String",
    "referenceName": null
   },
   "optional": true,
   "required": false,
   "description": "Gets or sets the last modified by."
  },
  {
   "containsDiscriminatedTypeValue": false,
   "jsonName": "lastModifiedTime",
   "name": "LastModifiedTime",
   "objectDefinition": {
    "type": "DateTime",
    "referenceName": null,
    "dateFormat": "RFC3339"
   },
   "optional": true,
   "required": false,
   "description": "Gets the last modified time."
  },
  {
   "containsDiscriminatedTypeValue": false,
   "jsonName": "privateEndpointConnections",
   "name": "PrivateEndpointConnections",
   "objectDefinition": {
    "type": "List",
    "referenceName": null,
    "nestedItem": {
     "type": "Reference",
     "referenceName": "PrivateEndpointConnection"
    }
   },
   "optional": true,
   "required": false,
   "description": "List of Automation operations supported by the Automation resource provider."
  },
  {
   "containsDiscriminatedTypeValue": false,
   "jsonName": "publicNetworkAccess",
   "name": "PublicNetworkAccess",
   "objectDefinition": {
    "type": "Boolean",
    "referenceName": null
   },
   "optional": true,
   "required": false,
   "description": "Indicates whether traffic on the non-ARM endpoint (Webhook/Agent) is allowed from the public internet"
  },
  {
   "containsDiscriminatedTypeValue": false,
   "jsonName": "sku",
   "name": "Sku",
   "objectDefinition": {
    "type": "Reference",
    "referenceName": "Sku"
   },
   "optional": true,
   "required": false,
   "description": "Gets or sets the SKU of account."
  },
  {
   "containsDiscriminatedTypeValue": false,
   "jsonName": "state",
   "name": "State",
   "objectDefinition": {
    "type": "Reference",
    "referenceName": "AutomationAccountState"
   },
   "optional": true,
   "required": false,
   "description": "Gets status of account."
  }
 ]
}