{
  "name": "TopologySingleResource",
  "fields": [
    {
      "containsDiscriminatedTypeValue": false,
      "description": "Azure resources connected to this resource which are in lower level in the topology view",
      "jsonName": "children",
      "name": "Children",
      "objectDefinition": {
        "type": "List",
        "nullable": false,
        "referenceName": null,
        "referenceNameIsCommonType": null,
        "nestedItem": {
          "type": "Reference",
          "nullable": false,
          "referenceName": "TopologySingleResourceChild",
          "referenceNameIsCommonType": null
        }
      },
      "optional": true,
      "readOnly": false,
      "required": false,
      "sensitive": false
    },
    {
      "containsDiscriminatedTypeValue": false,
      "description": "The location of this resource",
      "jsonName": "location",
      "name": "Location",
      "objectDefinition": {
        "type": "Location",
        "nullable": false,
        "referenceName": null,
        "referenceNameIsCommonType": null
      },
      "optional": true,
      "readOnly": false,
      "required": false,
      "sensitive": false
    },
    {
      "containsDiscriminatedTypeValue": false,
      "description": "Indicates the resource connectivity level to the Internet (InternetFacing, Internal ,etc.)",
      "jsonName": "networkZones",
      "name": "NetworkZones",
      "objectDefinition": {
        "type": "String",
        "nullable": false,
        "referenceName": null,
        "referenceNameIsCommonType": null
      },
      "optional": true,
      "readOnly": false,
      "required": false,
      "sensitive": false
    },
    {
      "containsDiscriminatedTypeValue": false,
      "description": "Azure resources connected to this resource which are in higher level in the topology view",
      "jsonName": "parents",
      "name": "Parents",
      "objectDefinition": {
        "type": "List",
        "nullable": false,
        "referenceName": null,
        "referenceNameIsCommonType": null,
        "nestedItem": {
          "type": "Reference",
          "nullable": false,
          "referenceName": "TopologySingleResourceParent",
          "referenceNameIsCommonType": null
        }
      },
      "optional": true,
      "readOnly": false,
      "required": false,
      "sensitive": false
    },
    {
      "containsDiscriminatedTypeValue": false,
      "description": "Indicates if the resource has security recommendations",
      "jsonName": "recommendationsExist",
      "name": "RecommendationsExist",
      "objectDefinition": {
        "type": "Boolean",
        "nullable": false,
        "referenceName": null,
        "referenceNameIsCommonType": null
      },
      "optional": true,
      "readOnly": false,
      "required": false,
      "sensitive": false
    },
    {
      "containsDiscriminatedTypeValue": false,
      "description": "Azure resource id",
      "jsonName": "resourceId",
      "name": "ResourceId",
      "objectDefinition": {
        "type": "String",
        "nullable": false,
        "referenceName": null,
        "referenceNameIsCommonType": null
      },
      "optional": true,
      "readOnly": false,
      "required": false,
      "sensitive": false
    },
    {
      "containsDiscriminatedTypeValue": false,
      "description": "The security severity of the resource",
      "jsonName": "severity",
      "name": "Severity",
      "objectDefinition": {
        "type": "String",
        "nullable": false,
        "referenceName": null,
        "referenceNameIsCommonType": null
      },
      "optional": true,
      "readOnly": false,
      "required": false,
      "sensitive": false
    },
    {
      "containsDiscriminatedTypeValue": false,
      "description": "Score of the resource based on its security severity",
      "jsonName": "topologyScore",
      "name": "TopologyScore",
      "objectDefinition": {
        "type": "Integer",
        "nullable": false,
        "referenceName": null,
        "referenceNameIsCommonType": null
      },
      "optional": true,
      "readOnly": false,
      "required": false,
      "sensitive": false
    }
  ],
  "IsParent": false
}