{
 "name": "QueryTextProperties",
 "fields": [
  {
   "containsDiscriminatedTypeValue": false,
   "jsonName": "queryId",
   "name": "QueryId",
   "objectDefinition": {
    "type": "String",
    "referenceName": null
   },
   "optional": true,
   "required": false,
   "description": ""
  },
  {
   "containsDiscriminatedTypeValue": false,
   "jsonName": "queryText",
   "name": "QueryText",
   "objectDefinition": {
    "type": "String",
    "referenceName": null
   },
   "optional": true,
   "required": false,
   "description": ""
  }
 ]
}