{
  "name": "Ingress",
  "fields": [
    {
      "containsDiscriminatedTypeValue": false,
      "jsonName": "allowInsecure",
      "name": "AllowInsecure",
      "objectDefinition": {
        "type": "Boolean",
        "nullable": false,
        "referenceName": null,
        "referenceNameIsCommonType": null
      },
      "optional": true,
      "readOnly": false,
      "required": false,
      "sensitive": false
    },
    {
      "containsDiscriminatedTypeValue": false,
      "jsonName": "external",
      "name": "External",
      "objectDefinition": {
        "type": "Boolean",
        "nullable": false,
        "referenceName": null,
        "referenceNameIsCommonType": null
      },
      "optional": true,
      "readOnly": false,
      "required": false,
      "sensitive": false
    },
    {
      "containsDiscriminatedTypeValue": false,
      "jsonName": "fqdn",
      "name": "Fqdn",
      "objectDefinition": {
        "type": "String",
        "nullable": false,
        "referenceName": null,
        "referenceNameIsCommonType": null
      },
      "optional": true,
      "readOnly": false,
      "required": false,
      "sensitive": false
    },
    {
      "containsDiscriminatedTypeValue": false,
      "jsonName": "targetPort",
      "name": "TargetPort",
      "objectDefinition": {
        "type": "Integer",
        "nullable": false,
        "referenceName": null,
        "referenceNameIsCommonType": null
      },
      "optional": true,
      "readOnly": false,
      "required": false,
      "sensitive": false
    },
    {
      "containsDiscriminatedTypeValue": false,
      "jsonName": "traffic",
      "name": "Traffic",
      "objectDefinition": {
        "type": "List",
        "nullable": false,
        "referenceName": null,
        "referenceNameIsCommonType": null,
        "nestedItem": {
          "type": "Reference",
          "nullable": false,
          "referenceName": "TrafficWeight",
          "referenceNameIsCommonType": null
        }
      },
      "optional": true,
      "readOnly": false,
      "required": false,
      "sensitive": false
    },
    {
      "containsDiscriminatedTypeValue": false,
      "jsonName": "transport",
      "name": "Transport",
      "objectDefinition": {
        "type": "Reference",
        "nullable": false,
        "referenceName": "IngressTransportMethod",
        "referenceNameIsCommonType": null
      },
      "optional": true,
      "readOnly": false,
      "required": false,
      "sensitive": false
    }
  ],
  "IsParent": false
}