{
  "name": "OfficeConsentProperties",
  "fields": [
    {
      "containsDiscriminatedTypeValue": false,
      "description": "Help to easily cascade among the data layers.",
      "jsonName": "consentId",
      "name": "ConsentId",
      "objectDefinition": {
        "type": "String",
        "nullable": false,
        "referenceName": null,
        "referenceNameIsCommonType": null
      },
      "optional": true,
      "readOnly": false,
      "required": false,
      "sensitive": false
    },
    {
      "containsDiscriminatedTypeValue": false,
      "description": "The tenantId of the Office365 with the consent.",
      "jsonName": "tenantId",
      "name": "TenantId",
      "objectDefinition": {
        "type": "String",
        "nullable": false,
        "referenceName": null,
        "referenceNameIsCommonType": null
      },
      "optional": true,
      "readOnly": false,
      "required": false,
      "sensitive": false
    }
  ],
  "IsParent": false
}