{
  "name": "ManagedClusterSecurityProfileImageCleaner",
  "fields": [
    {
      "containsDiscriminatedTypeValue": false,
      "jsonName": "enabled",
      "name": "Enabled",
      "objectDefinition": {
        "type": "Boolean",
        "referenceName": null
      },
      "optional": true,
      "required": false,
      "description": ""
    },
    {
      "containsDiscriminatedTypeValue": false,
      "jsonName": "intervalHours",
      "name": "IntervalHours",
      "objectDefinition": {
        "type": "Integer",
        "referenceName": null
      },
      "optional": true,
      "required": false,
      "description": ""
    }
  ]
}