{
  "name": "PropertyJobData",
  "fields": [
    {
      "containsDiscriminatedTypeValue": false,
      "jsonName": "path",
      "name": "Path",
      "objectDefinition": {
        "type": "String",
        "nullable": false,
        "referenceName": null,
        "referenceNameIsCommonType": null
      },
      "optional": false,
      "readOnly": false,
      "required": true,
      "sensitive": false
    },
    {
      "containsDiscriminatedTypeValue": false,
      "jsonName": "target",
      "name": "Target",
      "objectDefinition": {
        "type": "String",
        "nullable": false,
        "referenceName": null,
        "referenceNameIsCommonType": null
      },
      "optional": false,
      "readOnly": false,
      "required": true,
      "sensitive": false
    },
    {
      "containsDiscriminatedTypeValue": false,
      "jsonName": "value",
      "name": "Value",
      "objectDefinition": {
        "type": "RawObject",
        "nullable": false,
        "referenceName": null,
        "referenceNameIsCommonType": null
      },
      "optional": true,
      "readOnly": false,
      "required": false,
      "sensitive": false
    }
  ],
  "IsParent": false,
  "discriminatedParentModelName": "JobData",
  "discriminatedTypeValue": "property",
  "typeHintIn": "Type"
}