{
  "name": "SharedPrivateLinkResourceProperties",
  "fields": [
    {
      "containsDiscriminatedTypeValue": false,
      "jsonName": "groupId",
      "name": "GroupId",
      "objectDefinition": {
        "type": "String",
        "referenceName": null
      },
      "optional": true,
      "readOnly": false,
      "required": false,
      "sensitive": false
    },
    {
      "containsDiscriminatedTypeValue": false,
      "jsonName": "privateLink",
      "name": "PrivateLink",
      "objectDefinition": {
        "type": "Reference",
        "referenceName": "ResourceReference"
      },
      "optional": true,
      "readOnly": false,
      "required": false,
      "sensitive": false
    },
    {
      "containsDiscriminatedTypeValue": false,
      "jsonName": "privateLinkLocation",
      "name": "PrivateLinkLocation",
      "objectDefinition": {
        "type": "String",
        "referenceName": null
      },
      "optional": true,
      "readOnly": false,
      "required": false,
      "sensitive": false
    },
    {
      "containsDiscriminatedTypeValue": false,
      "jsonName": "requestMessage",
      "name": "RequestMessage",
      "objectDefinition": {
        "type": "String",
        "referenceName": null
      },
      "optional": true,
      "readOnly": false,
      "required": false,
      "sensitive": false
    },
    {
      "containsDiscriminatedTypeValue": false,
      "jsonName": "status",
      "name": "Status",
      "objectDefinition": {
        "type": "Reference",
        "referenceName": "SharedPrivateLinkResourceStatus"
      },
      "optional": true,
      "readOnly": false,
      "required": false,
      "sensitive": false
    }
  ]
}