{
  "name": "WorkloadGroupProperties",
  "fields": [
    {
      "containsDiscriminatedTypeValue": false,
      "description": "The workload group importance level.",
      "jsonName": "importance",
      "name": "Importance",
      "objectDefinition": {
        "type": "String",
        "nullable": false,
        "referenceName": null,
        "referenceNameIsCommonType": null
      },
      "optional": true,
      "readOnly": false,
      "required": false,
      "sensitive": false
    },
    {
      "containsDiscriminatedTypeValue": false,
      "description": "The workload group cap percentage resource.",
      "jsonName": "maxResourcePercent",
      "name": "MaxResourcePercent",
      "objectDefinition": {
        "type": "Integer",
        "nullable": false,
        "referenceName": null,
        "referenceNameIsCommonType": null
      },
      "optional": false,
      "readOnly": false,
      "required": true,
      "sensitive": false
    },
    {
      "containsDiscriminatedTypeValue": false,
      "description": "The workload group request maximum grant percentage.",
      "jsonName": "maxResourcePercentPerRequest",
      "name": "MaxResourcePercentPerRequest",
      "objectDefinition": {
        "type": "Float",
        "nullable": false,
        "referenceName": null,
        "referenceNameIsCommonType": null
      },
      "optional": true,
      "readOnly": false,
      "required": false,
      "sensitive": false
    },
    {
      "containsDiscriminatedTypeValue": false,
      "description": "The workload group minimum percentage resource.",
      "jsonName": "minResourcePercent",
      "name": "MinResourcePercent",
      "objectDefinition": {
        "type": "Integer",
        "nullable": false,
        "referenceName": null,
        "referenceNameIsCommonType": null
      },
      "optional": false,
      "readOnly": false,
      "required": true,
      "sensitive": false
    },
    {
      "containsDiscriminatedTypeValue": false,
      "description": "The workload group request minimum grant percentage.",
      "jsonName": "minResourcePercentPerRequest",
      "name": "MinResourcePercentPerRequest",
      "objectDefinition": {
        "type": "Float",
        "nullable": false,
        "referenceName": null,
        "referenceNameIsCommonType": null
      },
      "optional": false,
      "readOnly": false,
      "required": true,
      "sensitive": false
    },
    {
      "containsDiscriminatedTypeValue": false,
      "description": "The workload group query execution timeout.",
      "jsonName": "queryExecutionTimeout",
      "name": "QueryExecutionTimeout",
      "objectDefinition": {
        "type": "Integer",
        "nullable": false,
        "referenceName": null,
        "referenceNameIsCommonType": null
      },
      "optional": true,
      "readOnly": false,
      "required": false,
      "sensitive": false
    }
  ],
  "IsParent": false
}