{
  "name": "ClusterProperties",
  "fields": [
    {
      "containsDiscriminatedTypeValue": false,
      "jsonName": "acceptedAudiences",
      "name": "AcceptedAudiences",
      "objectDefinition": {
        "type": "List",
        "nullable": false,
        "referenceName": null,
        "referenceNameIsCommonType": null,
        "nestedItem": {
          "type": "Reference",
          "nullable": false,
          "referenceName": "AcceptedAudiences",
          "referenceNameIsCommonType": null
        }
      },
      "optional": true,
      "readOnly": false,
      "required": false,
      "sensitive": false
    },
    {
      "containsDiscriminatedTypeValue": false,
      "jsonName": "allowedFqdnList",
      "name": "AllowedFqdnList",
      "objectDefinition": {
        "type": "List",
        "nullable": false,
        "referenceName": null,
        "referenceNameIsCommonType": null,
        "nestedItem": {
          "type": "String",
          "nullable": false,
          "referenceName": null,
          "referenceNameIsCommonType": null
        }
      },
      "optional": true,
      "readOnly": false,
      "required": false,
      "sensitive": false
    },
    {
      "containsDiscriminatedTypeValue": false,
      "jsonName": "allowedIpRangeList",
      "name": "AllowedIPRangeList",
      "objectDefinition": {
        "type": "List",
        "nullable": false,
        "referenceName": null,
        "referenceNameIsCommonType": null,
        "nestedItem": {
          "type": "String",
          "nullable": false,
          "referenceName": null,
          "referenceNameIsCommonType": null
        }
      },
      "optional": true,
      "readOnly": false,
      "required": false,
      "sensitive": false
    },
    {
      "containsDiscriminatedTypeValue": false,
      "jsonName": "dataIngestionUri",
      "name": "DataIngestionUri",
      "objectDefinition": {
        "type": "String",
        "nullable": false,
        "referenceName": null,
        "referenceNameIsCommonType": null
      },
      "optional": true,
      "readOnly": false,
      "required": false,
      "sensitive": false
    },
    {
      "containsDiscriminatedTypeValue": false,
      "jsonName": "enableAutoStop",
      "name": "EnableAutoStop",
      "objectDefinition": {
        "type": "Boolean",
        "nullable": false,
        "referenceName": null,
        "referenceNameIsCommonType": null
      },
      "optional": true,
      "readOnly": false,
      "required": false,
      "sensitive": false
    },
    {
      "containsDiscriminatedTypeValue": false,
      "jsonName": "enableDiskEncryption",
      "name": "EnableDiskEncryption",
      "objectDefinition": {
        "type": "Boolean",
        "nullable": false,
        "referenceName": null,
        "referenceNameIsCommonType": null
      },
      "optional": true,
      "readOnly": false,
      "required": false,
      "sensitive": false
    },
    {
      "containsDiscriminatedTypeValue": false,
      "jsonName": "enableDoubleEncryption",
      "name": "EnableDoubleEncryption",
      "objectDefinition": {
        "type": "Boolean",
        "nullable": false,
        "referenceName": null,
        "referenceNameIsCommonType": null
      },
      "optional": true,
      "readOnly": false,
      "required": false,
      "sensitive": false
    },
    {
      "containsDiscriminatedTypeValue": false,
      "jsonName": "enablePurge",
      "name": "EnablePurge",
      "objectDefinition": {
        "type": "Boolean",
        "nullable": false,
        "referenceName": null,
        "referenceNameIsCommonType": null
      },
      "optional": true,
      "readOnly": false,
      "required": false,
      "sensitive": false
    },
    {
      "containsDiscriminatedTypeValue": false,
      "jsonName": "enableStreamingIngest",
      "name": "EnableStreamingIngest",
      "objectDefinition": {
        "type": "Boolean",
        "nullable": false,
        "referenceName": null,
        "referenceNameIsCommonType": null
      },
      "optional": true,
      "readOnly": false,
      "required": false,
      "sensitive": false
    },
    {
      "containsDiscriminatedTypeValue": false,
      "jsonName": "engineType",
      "name": "EngineType",
      "objectDefinition": {
        "type": "Reference",
        "nullable": false,
        "referenceName": "EngineType",
        "referenceNameIsCommonType": null
      },
      "optional": true,
      "readOnly": false,
      "required": false,
      "sensitive": false
    },
    {
      "containsDiscriminatedTypeValue": false,
      "jsonName": "keyVaultProperties",
      "name": "KeyVaultProperties",
      "objectDefinition": {
        "type": "Reference",
        "nullable": false,
        "referenceName": "KeyVaultProperties",
        "referenceNameIsCommonType": null
      },
      "optional": true,
      "readOnly": false,
      "required": false,
      "sensitive": false
    },
    {
      "containsDiscriminatedTypeValue": false,
      "jsonName": "languageExtensions",
      "name": "LanguageExtensions",
      "objectDefinition": {
        "type": "Reference",
        "nullable": false,
        "referenceName": "LanguageExtensionsList",
        "referenceNameIsCommonType": null
      },
      "optional": true,
      "readOnly": false,
      "required": false,
      "sensitive": false
    },
    {
      "containsDiscriminatedTypeValue": false,
      "jsonName": "migrationCluster",
      "name": "MigrationCluster",
      "objectDefinition": {
        "type": "Reference",
        "nullable": false,
        "referenceName": "MigrationClusterProperties",
        "referenceNameIsCommonType": null
      },
      "optional": true,
      "readOnly": false,
      "required": false,
      "sensitive": false
    },
    {
      "containsDiscriminatedTypeValue": false,
      "jsonName": "optimizedAutoscale",
      "name": "OptimizedAutoscale",
      "objectDefinition": {
        "type": "Reference",
        "nullable": false,
        "referenceName": "OptimizedAutoscale",
        "referenceNameIsCommonType": null
      },
      "optional": true,
      "readOnly": false,
      "required": false,
      "sensitive": false
    },
    {
      "containsDiscriminatedTypeValue": false,
      "jsonName": "privateEndpointConnections",
      "name": "PrivateEndpointConnections",
      "objectDefinition": {
        "type": "List",
        "nullable": false,
        "referenceName": null,
        "referenceNameIsCommonType": null,
        "nestedItem": {
          "type": "Reference",
          "nullable": false,
          "referenceName": "PrivateEndpointConnection",
          "referenceNameIsCommonType": null
        }
      },
      "optional": true,
      "readOnly": false,
      "required": false,
      "sensitive": false
    },
    {
      "containsDiscriminatedTypeValue": false,
      "jsonName": "provisioningState",
      "name": "ProvisioningState",
      "objectDefinition": {
        "type": "Reference",
        "nullable": false,
        "referenceName": "ProvisioningState",
        "referenceNameIsCommonType": null
      },
      "optional": true,
      "readOnly": false,
      "required": false,
      "sensitive": false
    },
    {
      "containsDiscriminatedTypeValue": false,
      "jsonName": "publicIPType",
      "name": "PublicIPType",
      "objectDefinition": {
        "type": "Reference",
        "nullable": false,
        "referenceName": "PublicIPType",
        "referenceNameIsCommonType": null
      },
      "optional": true,
      "readOnly": false,
      "required": false,
      "sensitive": false
    },
    {
      "containsDiscriminatedTypeValue": false,
      "jsonName": "publicNetworkAccess",
      "name": "PublicNetworkAccess",
      "objectDefinition": {
        "type": "Reference",
        "nullable": false,
        "referenceName": "PublicNetworkAccess",
        "referenceNameIsCommonType": null
      },
      "optional": true,
      "readOnly": false,
      "required": false,
      "sensitive": false
    },
    {
      "containsDiscriminatedTypeValue": false,
      "jsonName": "restrictOutboundNetworkAccess",
      "name": "RestrictOutboundNetworkAccess",
      "objectDefinition": {
        "type": "Reference",
        "nullable": false,
        "referenceName": "ClusterNetworkAccessFlag",
        "referenceNameIsCommonType": null
      },
      "optional": true,
      "readOnly": false,
      "required": false,
      "sensitive": false
    },
    {
      "containsDiscriminatedTypeValue": false,
      "jsonName": "state",
      "name": "State",
      "objectDefinition": {
        "type": "Reference",
        "nullable": false,
        "referenceName": "State",
        "referenceNameIsCommonType": null
      },
      "optional": true,
      "readOnly": false,
      "required": false,
      "sensitive": false
    },
    {
      "containsDiscriminatedTypeValue": false,
      "jsonName": "stateReason",
      "name": "StateReason",
      "objectDefinition": {
        "type": "String",
        "nullable": false,
        "referenceName": null,
        "referenceNameIsCommonType": null
      },
      "optional": true,
      "readOnly": false,
      "required": false,
      "sensitive": false
    },
    {
      "containsDiscriminatedTypeValue": false,
      "jsonName": "trustedExternalTenants",
      "name": "TrustedExternalTenants",
      "objectDefinition": {
        "type": "List",
        "nullable": false,
        "referenceName": null,
        "referenceNameIsCommonType": null,
        "nestedItem": {
          "type": "Reference",
          "nullable": false,
          "referenceName": "TrustedExternalTenant",
          "referenceNameIsCommonType": null
        }
      },
      "optional": true,
      "readOnly": false,
      "required": false,
      "sensitive": false
    },
    {
      "containsDiscriminatedTypeValue": false,
      "jsonName": "uri",
      "name": "Uri",
      "objectDefinition": {
        "type": "String",
        "nullable": false,
        "referenceName": null,
        "referenceNameIsCommonType": null
      },
      "optional": true,
      "readOnly": false,
      "required": false,
      "sensitive": false
    },
    {
      "containsDiscriminatedTypeValue": false,
      "jsonName": "virtualClusterGraduationProperties",
      "name": "VirtualClusterGraduationProperties",
      "objectDefinition": {
        "type": "String",
        "nullable": false,
        "referenceName": null,
        "referenceNameIsCommonType": null
      },
      "optional": true,
      "readOnly": false,
      "required": false,
      "sensitive": false
    },
    {
      "containsDiscriminatedTypeValue": false,
      "jsonName": "virtualNetworkConfiguration",
      "name": "VirtualNetworkConfiguration",
      "objectDefinition": {
        "type": "Reference",
        "nullable": false,
        "referenceName": "VirtualNetworkConfiguration",
        "referenceNameIsCommonType": null
      },
      "optional": true,
      "readOnly": false,
      "required": false,
      "sensitive": false
    }
  ],
  "IsParent": false
}