{
  "name": "VirtualMachineCaptureResult",
  "fields": [
    {
      "containsDiscriminatedTypeValue": false,
      "description": "the version of the content",
      "jsonName": "contentVersion",
      "name": "ContentVersion",
      "objectDefinition": {
        "type": "String",
        "nullable": false,
        "referenceName": null,
        "referenceNameIsCommonType": null
      },
      "optional": true,
      "readOnly": false,
      "required": false,
      "sensitive": false
    },
    {
      "containsDiscriminatedTypeValue": false,
      "description": "Resource Id",
      "jsonName": "id",
      "name": "Id",
      "objectDefinition": {
        "type": "String",
        "nullable": false,
        "referenceName": null,
        "referenceNameIsCommonType": null
      },
      "optional": true,
      "readOnly": false,
      "required": false,
      "sensitive": false
    },
    {
      "containsDiscriminatedTypeValue": false,
      "description": "parameters of the captured virtual machine",
      "jsonName": "parameters",
      "name": "Parameters",
      "objectDefinition": {
        "type": "RawObject",
        "nullable": false,
        "referenceName": null,
        "referenceNameIsCommonType": null
      },
      "optional": true,
      "readOnly": false,
      "required": false,
      "sensitive": false
    },
    {
      "containsDiscriminatedTypeValue": false,
      "description": "a list of resource items of the captured virtual machine",
      "jsonName": "resources",
      "name": "Resources",
      "objectDefinition": {
        "type": "List",
        "nullable": false,
        "referenceName": null,
        "referenceNameIsCommonType": null,
        "nestedItem": {
          "type": "RawObject",
          "nullable": false,
          "referenceName": null,
          "referenceNameIsCommonType": null
        }
      },
      "optional": true,
      "readOnly": false,
      "required": false,
      "sensitive": false
    },
    {
      "containsDiscriminatedTypeValue": false,
      "description": "the schema of the captured virtual machine",
      "jsonName": "$schema",
      "name": "Schema",
      "objectDefinition": {
        "type": "String",
        "nullable": false,
        "referenceName": null,
        "referenceNameIsCommonType": null
      },
      "optional": true,
      "readOnly": false,
      "required": false,
      "sensitive": false
    }
  ],
  "IsParent": false
}