{
  "name": "Job",
  "fields": [
    {
      "containsDiscriminatedTypeValue": false,
      "dateFormat": "RFC3339",
      "description": "The UTC date and time at which the job completed.",
      "jsonName": "endTime",
      "name": "EndTime",
      "objectDefinition": {
        "type": "DateTime",
        "nullable": false,
        "referenceName": null,
        "referenceNameIsCommonType": null
      },
      "optional": true,
      "readOnly": false,
      "required": false,
      "sensitive": false
    },
    {
      "containsDiscriminatedTypeValue": false,
      "description": "The error details.",
      "jsonName": "error",
      "name": "Error",
      "objectDefinition": {
        "type": "Reference",
        "nullable": false,
        "referenceName": "JobErrorDetails",
        "referenceNameIsCommonType": null
      },
      "optional": true,
      "readOnly": false,
      "required": false,
      "sensitive": false
    },
    {
      "containsDiscriminatedTypeValue": false,
      "description": "The path ID that uniquely identifies the object.",
      "jsonName": "id",
      "name": "Id",
      "objectDefinition": {
        "type": "String",
        "nullable": false,
        "referenceName": null,
        "referenceNameIsCommonType": null
      },
      "optional": true,
      "readOnly": false,
      "required": false,
      "sensitive": false
    },
    {
      "containsDiscriminatedTypeValue": false,
      "description": "The name of the object.",
      "jsonName": "name",
      "name": "Name",
      "objectDefinition": {
        "type": "String",
        "nullable": false,
        "referenceName": null,
        "referenceNameIsCommonType": null
      },
      "optional": true,
      "readOnly": false,
      "required": false,
      "sensitive": false
    },
    {
      "containsDiscriminatedTypeValue": false,
      "description": "The percentage of the job that is complete.",
      "jsonName": "percentComplete",
      "name": "PercentComplete",
      "objectDefinition": {
        "type": "Integer",
        "nullable": false,
        "referenceName": null,
        "referenceNameIsCommonType": null
      },
      "optional": true,
      "readOnly": false,
      "required": false,
      "sensitive": false
    },
    {
      "containsDiscriminatedTypeValue": false,
      "description": "The properties of the job.",
      "jsonName": "properties",
      "name": "Properties",
      "objectDefinition": {
        "type": "Reference",
        "nullable": false,
        "referenceName": "JobProperties",
        "referenceNameIsCommonType": null
      },
      "optional": true,
      "readOnly": false,
      "required": false,
      "sensitive": false
    },
    {
      "containsDiscriminatedTypeValue": false,
      "dateFormat": "RFC3339",
      "description": "The UTC date and time at which the job started.",
      "jsonName": "startTime",
      "name": "StartTime",
      "objectDefinition": {
        "type": "DateTime",
        "nullable": false,
        "referenceName": null,
        "referenceNameIsCommonType": null
      },
      "optional": true,
      "readOnly": false,
      "required": false,
      "sensitive": false
    },
    {
      "containsDiscriminatedTypeValue": false,
      "description": "The current status of the job.",
      "jsonName": "status",
      "name": "Status",
      "objectDefinition": {
        "type": "Reference",
        "nullable": false,
        "referenceName": "JobStatus",
        "referenceNameIsCommonType": null
      },
      "optional": true,
      "readOnly": false,
      "required": false,
      "sensitive": false
    },
    {
      "containsDiscriminatedTypeValue": false,
      "description": "The hierarchical type of the object.",
      "jsonName": "type",
      "name": "Type",
      "objectDefinition": {
        "type": "String",
        "nullable": false,
        "referenceName": null,
        "referenceNameIsCommonType": null
      },
      "optional": true,
      "readOnly": false,
      "required": false,
      "sensitive": false
    }
  ],
  "IsParent": false
}