{
 "name": "ServerlessUpstreamSettings",
 "fields": [
  {
   "containsDiscriminatedTypeValue": false,
   "jsonName": "templates",
   "name": "Templates",
   "objectDefinition": {
    "type": "List",
    "referenceName": null,
    "nestedItem": {
     "type": "Reference",
     "referenceName": "UpstreamTemplate"
    }
   },
   "optional": true,
   "required": false,
   "description": "Gets or sets the list of Upstream URL templates. Order matters, and the first matching template takes effects."
  }
 ]
}