{
  "name": "LicenseProfileMachineInstanceView",
  "fields": [
    {
      "containsDiscriminatedTypeValue": false,
      "jsonName": "esuProfile",
      "name": "EsuProfile",
      "objectDefinition": {
        "type": "Reference",
        "nullable": false,
        "referenceName": "LicenseProfileMachineInstanceViewEsuProperties",
        "referenceNameIsCommonType": null
      },
      "optional": true,
      "readOnly": false,
      "required": false,
      "sensitive": false
    },
    {
      "containsDiscriminatedTypeValue": false,
      "description": "Indicates the license channel.",
      "jsonName": "licenseChannel",
      "name": "LicenseChannel",
      "objectDefinition": {
        "type": "String",
        "nullable": false,
        "referenceName": null,
        "referenceNameIsCommonType": null
      },
      "optional": true,
      "readOnly": false,
      "required": false,
      "sensitive": false
    },
    {
      "containsDiscriminatedTypeValue": false,
      "description": "Indicates the license status of the OS.",
      "jsonName": "licenseStatus",
      "name": "LicenseStatus",
      "objectDefinition": {
        "type": "Reference",
        "nullable": false,
        "referenceName": "LicenseStatus",
        "referenceNameIsCommonType": null
      },
      "optional": true,
      "readOnly": false,
      "required": false,
      "sensitive": false
    },
    {
      "containsDiscriminatedTypeValue": false,
      "description": "Hybrid Compute Product Profile properties",
      "jsonName": "productProfile",
      "name": "ProductProfile",
      "objectDefinition": {
        "type": "Reference",
        "nullable": false,
        "referenceName": "LicenseProfileArmProductProfileProperties",
        "referenceNameIsCommonType": null
      },
      "optional": true,
      "readOnly": false,
      "required": false,
      "sensitive": false
    },
    {
      "containsDiscriminatedTypeValue": false,
      "jsonName": "softwareAssurance",
      "name": "SoftwareAssurance",
      "objectDefinition": {
        "type": "Reference",
        "nullable": false,
        "referenceName": "LicenseProfileMachineInstanceViewSoftwareAssurance",
        "referenceNameIsCommonType": null
      },
      "optional": true,
      "readOnly": false,
      "required": false,
      "sensitive": false
    }
  ],
  "IsParent": false
}