{
  "name": "AlertPropertyMapping",
  "fields": [
    {
      "containsDiscriminatedTypeValue": false,
      "jsonName": "alertProperty",
      "name": "AlertProperty",
      "objectDefinition": {
        "type": "Reference",
        "nullable": false,
        "referenceName": "AlertProperty",
        "referenceNameIsCommonType": null
      },
      "optional": true,
      "readOnly": false,
      "required": false,
      "sensitive": false
    },
    {
      "containsDiscriminatedTypeValue": false,
      "description": "the column name to use to override this property",
      "jsonName": "value",
      "name": "Value",
      "objectDefinition": {
        "type": "String",
        "nullable": false,
        "referenceName": null,
        "referenceNameIsCommonType": null
      },
      "optional": true,
      "readOnly": false,
      "required": false,
      "sensitive": false
    }
  ],
  "IsParent": false
}