{
 "name": "SoftwareUpdateConfigurationRunTaskProperties",
 "fields": [
  {
   "containsDiscriminatedTypeValue": false,
   "jsonName": "jobId",
   "name": "JobId",
   "objectDefinition": {
    "type": "String",
    "referenceName": null
   },
   "optional": true,
   "required": false,
   "description": "The job id of the task."
  },
  {
   "containsDiscriminatedTypeValue": false,
   "jsonName": "source",
   "name": "Source",
   "objectDefinition": {
    "type": "String",
    "referenceName": null
   },
   "optional": true,
   "required": false,
   "description": "The name of the source of the task."
  },
  {
   "containsDiscriminatedTypeValue": false,
   "jsonName": "status",
   "name": "Status",
   "objectDefinition": {
    "type": "String",
    "referenceName": null
   },
   "optional": true,
   "required": false,
   "description": "The status of the task."
  }
 ]
}