{
  "name": "HostKeys",
  "fields": [
    {
      "containsDiscriminatedTypeValue": false,
      "jsonName": "functionKeys",
      "name": "FunctionKeys",
      "objectDefinition": {
        "type": "Dictionary",
        "nullable": false,
        "referenceName": null,
        "referenceNameIsCommonType": null,
        "nestedItem": {
          "type": "String",
          "nullable": false,
          "referenceName": null,
          "referenceNameIsCommonType": null
        }
      },
      "optional": true,
      "readOnly": false,
      "required": false,
      "sensitive": false
    },
    {
      "containsDiscriminatedTypeValue": false,
      "jsonName": "masterKey",
      "name": "MasterKey",
      "objectDefinition": {
        "type": "String",
        "nullable": false,
        "referenceName": null,
        "referenceNameIsCommonType": null
      },
      "optional": true,
      "readOnly": false,
      "required": false,
      "sensitive": false
    },
    {
      "containsDiscriminatedTypeValue": false,
      "jsonName": "systemKeys",
      "name": "SystemKeys",
      "objectDefinition": {
        "type": "Dictionary",
        "nullable": false,
        "referenceName": null,
        "referenceNameIsCommonType": null,
        "nestedItem": {
          "type": "String",
          "nullable": false,
          "referenceName": null,
          "referenceNameIsCommonType": null
        }
      },
      "optional": true,
      "readOnly": false,
      "required": false,
      "sensitive": false
    }
  ],
  "IsParent": false
}