{
  "name": "Update",
  "contentType": "application/json; charset=utf-8",
  "description": "",
  "expectedStatusCodes": [
    200,
    202
  ],
  "longRunning": true,
  "httpMethod": "PATCH",
  "resourceIdName": "CloudId",
  "requestObject": {
    "type": "Reference",
    "nullable": false,
    "referenceName": "CloudTagsUpdate",
    "referenceNameIsCommonType": null
  },
  "responseObject": {
    "type": "Reference",
    "nullable": false,
    "referenceName": "Cloud",
    "referenceNameIsCommonType": null
  }
}