{
  "name": "WebApplicationFirewallStatus",
  "fields": [
    {
      "containsDiscriminatedTypeValue": false,
      "description": "Package containing attack signatures for the NGINX App Protect Web Application Firewall (WAF).",
      "jsonName": "attackSignaturesPackage",
      "name": "AttackSignaturesPackage",
      "objectDefinition": {
        "type": "Reference",
        "nullable": false,
        "referenceName": "WebApplicationFirewallPackage",
        "referenceNameIsCommonType": null
      },
      "optional": true,
      "readOnly": false,
      "required": false,
      "sensitive": false
    },
    {
      "containsDiscriminatedTypeValue": false,
      "description": "Package containing bot signatures for the NGINX App Protect Web Application Firewall (WAF).",
      "jsonName": "botSignaturesPackage",
      "name": "BotSignaturesPackage",
      "objectDefinition": {
        "type": "Reference",
        "nullable": false,
        "referenceName": "WebApplicationFirewallPackage",
        "referenceNameIsCommonType": null
      },
      "optional": true,
      "readOnly": false,
      "required": false,
      "sensitive": false
    },
    {
      "containsDiscriminatedTypeValue": false,
      "description": "Versions of the NGINX App Protect Web Application Firewall (WAF) components.",
      "jsonName": "componentVersions",
      "name": "ComponentVersions",
      "objectDefinition": {
        "type": "Reference",
        "nullable": false,
        "referenceName": "WebApplicationFirewallComponentVersions",
        "referenceNameIsCommonType": null
      },
      "optional": true,
      "readOnly": false,
      "required": false,
      "sensitive": false
    },
    {
      "containsDiscriminatedTypeValue": false,
      "description": "Package containing threat campaigns for the NGINX App Protect Web Application Firewall (WAF).",
      "jsonName": "threatCampaignsPackage",
      "name": "ThreatCampaignsPackage",
      "objectDefinition": {
        "type": "Reference",
        "nullable": false,
        "referenceName": "WebApplicationFirewallPackage",
        "referenceNameIsCommonType": null
      },
      "optional": true,
      "readOnly": false,
      "required": false,
      "sensitive": false
    }
  ],
  "IsParent": false
}