{
  "name": "Dapr",
  "fields": [
    {
      "containsDiscriminatedTypeValue": false,
      "jsonName": "appId",
      "name": "AppId",
      "objectDefinition": {
        "type": "String",
        "nullable": false,
        "referenceName": null,
        "referenceNameIsCommonType": null
      },
      "optional": true,
      "readOnly": false,
      "required": false,
      "sensitive": false
    },
    {
      "containsDiscriminatedTypeValue": false,
      "jsonName": "appPort",
      "name": "AppPort",
      "objectDefinition": {
        "type": "Integer",
        "nullable": false,
        "referenceName": null,
        "referenceNameIsCommonType": null
      },
      "optional": true,
      "readOnly": false,
      "required": false,
      "sensitive": false
    },
    {
      "containsDiscriminatedTypeValue": false,
      "jsonName": "components",
      "name": "Components",
      "objectDefinition": {
        "type": "List",
        "nullable": false,
        "referenceName": null,
        "referenceNameIsCommonType": null,
        "nestedItem": {
          "type": "Reference",
          "nullable": false,
          "referenceName": "DaprComponent",
          "referenceNameIsCommonType": null
        }
      },
      "optional": true,
      "readOnly": false,
      "required": false,
      "sensitive": false
    },
    {
      "containsDiscriminatedTypeValue": false,
      "jsonName": "enabled",
      "name": "Enabled",
      "objectDefinition": {
        "type": "Boolean",
        "nullable": false,
        "referenceName": null,
        "referenceNameIsCommonType": null
      },
      "optional": true,
      "readOnly": false,
      "required": false,
      "sensitive": false
    }
  ],
  "IsParent": false
}